tool_decorator/__init__.py
tool_decorator/decorator.py
tool_decorator-0.1.0.dist-info/METADATA
tool_decorator-0.1.0.dist-info/WHEEL
tool_decorator-0.1.0.dist-info/licenses/LICENSE
tool_decorator-0.1.0.dist-info/RECORD
