Metadata-Version: 2.4
Name: tool_decorator
Version: 0.1.0
Summary: A decorator for creating Anthropic tool definitions
Project-URL: Homepage, https://github.com/joaompinto/tool_decorator
Project-URL: Bug Tracker, https://github.com/joaompinto/tool_decorator/issues
Author-email: João Pinto <lamego.pinto@gmail.com>
License-File: LICENSE
Classifier: License :: OSI Approved :: MIT License
Classifier: Operating System :: OS Independent
Classifier: Programming Language :: Python :: 3
Classifier: Programming Language :: Python :: 3.8
Classifier: Programming Language :: Python :: 3.9
Classifier: Programming Language :: Python :: 3.10
Classifier: Programming Language :: Python :: 3.11
Requires-Python: >=3.8
